rda/README.md
rda/__init__.py
rda/rda.py
rda-0.0.1.dist-info/METADATA
rda-0.0.1.dist-info/WHEEL
rda-0.0.1.dist-info/entry_points.txt
rda-0.0.1.dist-info/RECORD
