Metadata-Version: 2.1
Name: rda
Version: 0.0.1
Summary: The rda package provides a Python-based toolkit for automating and managing remote desktop actions, including capturing and replaying keyboard and mouse events
Author: tejus3131
Author-email: tejus3131@gmail.com
Requires-Python: >=3.12,<4.0
Classifier: Programming Language :: Python :: 3
Classifier: Programming Language :: Python :: 3.12
Requires-Dist: numpy (>=2.0.0,<3.0.0)
Requires-Dist: opencv-python (>=4.10.0.84,<5.0.0.0)
Requires-Dist: pillow (>=10.3.0,<11.0.0)
Requires-Dist: pyautogui (>=0.9.54,<0.10.0)
Requires-Dist: pygame (>=2.5.2,<3.0.0)
Requires-Dist: pynput (>=1.7.7,<2.0.0)
Requires-Dist: requests (>=2.32.3,<3.0.0)
